{"patch": [{"file_path": "src/main/java/org/jsoup/parser/HtmlTreeBuilder.java", "buggy_line numbers": [468, 469, 470, 471], "fix_type": "replace", "fix": ["int bottom = stack.size() -1;", "//    <If running in fragment case, bottom is greater than stack size by 1>", "//    bottom is stack size (present HTML element) when parsing document", "if (bottom > MaxScopeSearchDepth)", "bottom = MaxScopeSearchDepth;"], "developer_fix": ["final int bottom = stack.size() -1;"]}], "iter_path": "Iteration 1 with loc 1/1. Iteration 2 with loc 1/1. ", "time_cost": 92.97777771949768}