{"patch": [{"file_path": "src/java/org/apache/commons/math/stat/Frequency.java", "buggy_line numbers": [110], "fix_type": "insert", "fix": ["if (v instanceof Comparable<?>) {"], "developer_fix": ["if (v instanceof Comparable<?>){"]}, {"file_path": "src/java/org/apache/commons/math/stat/Frequency.java", "buggy_line numbers": [111], "fix_type": "insert", "fix": ["} else {", "throw new IllegalArgumentException(\"Object must be Comparable\");", "}"], "developer_fix": ["} else {", "throw new IllegalArgumentException(\"Object must implement Comparable\");", "}"]}], "iter_path": "Iteration 1 with loc 1/2. Iteration 2 with loc 1/2. Iteration 3 with loc 2/2. ", "time_cost": 541.6601588726044}